[{"year": "2024", "q": "2024-07", "category": "41 - 45", "data": 1699},{"year": "2024", "q": "2024-07", "category": "> 65", "data": 16},{"year": "2024", "q": "2024-07", "category": "25-", "data": 327},{"year": "2024", "q": "2024-07", "category": "61 - 65", "data": 327},{"year": "2024", "q": "2024-07", "category": "56 - 60", "data": 721},{"year": "2024", "q": "2024-07", "category": "26 - 30", "data": 716},{"year": "2024", "q": "2024-07", "category": "46 - 50", "data": 1585},{"year": "2024", "q": "2024-07", "category": "31 - 35", "data": 1262},{"year": "2024", "q": "2024-07", "category": "36 - 40", "data": 1505},{"year": "2024", "q": "2024-07", "category": "51 - 55", "data": 1262},{"year": "2024", "q": "2024-06", "category": "56 - 60", "data": 724},{"year": "2024", "q": "2024-06", "category": "26 - 30", "data": 719},{"year": "2024", "q": "2024-06", "category": "41 - 45", "data": 1727},{"year": "2024", "q": "2024-06", "category": "46 - 50", "data": 1594},{"year": "2024", "q": "2024-06", "category": "25-", "data": 326},{"year": "2024", "q": "2024-06", "category": "31 - 35", "data": 1273},{"year": "2024", "q": "2024-06", "category": "36 - 40", "data": 1520},{"year": "2024", "q": "2024-06", "category": "51 - 55", "data": 1265},{"year": "2024", "q": "2024-06", "category": "61 - 65", "data": 334},{"year": "2024", "q": "2024-06", "category": "> 65", "data": 18},{"year": "2024", "q": "2024-05", "category": "41 - 45", "data": 1726},{"year": "2024", "q": "2024-05", "category": "46 - 50", "data": 1592},{"year": "2024", "q": "2024-05", "category": "51 - 55", "data": 1260},{"year": "2024", "q": "2024-05", "category": "26 - 30", "data": 721},{"year": "2024", "q": "2024-05", "category": "61 - 65", "data": 339},{"year": "2024", "q": "2024-05", "category": "31 - 35", "data": 1271},{"year": "2024", "q": "2024-05", "category": "36 - 40", "data": 1519},{"year": "2024", "q": "2024-05", "category": "25-", "data": 322},{"year": "2024", "q": "2024-05", "category": "> 65", "data": 18},{"year": "2024", "q": "2024-05", "category": "56 - 60", "data": 725},{"year": "2024", "q": "2024-04", "category": "26 - 30", "data": 717},{"year": "2024", "q": "2024-04", "category": "61 - 65", "data": 365},{"year": "2024", "q": "2024-04", "category": "> 65", "data": 19},{"year": "2024", "q": "2024-04", "category": "41 - 45", "data": 1731},{"year": "2024", "q": "2024-04", "category": "46 - 50", "data": 1591},{"year": "2024", "q": "2024-04", "category": "31 - 35", "data": 1273},{"year": "2024", "q": "2024-04", "category": "51 - 55", "data": 1263},{"year": "2024", "q": "2024-04", "category": "25-", "data": 319},{"year": "2024", "q": "2024-04", "category": "36 - 40", "data": 1520},{"year": "2024", "q": "2024-04", "category": "56 - 60", "data": 727},{"year": "2024", "q": "2024-03", "category": "51 - 55", "data": 1264},{"year": "2024", "q": "2024-03", "category": "26 - 30", "data": 705},{"year": "2024", "q": "2024-03", "category": "41 - 45", "data": 1727},{"year": "2024", "q": "2024-03", "category": "25-", "data": 315},{"year": "2024", "q": "2024-03", "category": "> 65", "data": 19},{"year": "2024", "q": "2024-03", "category": "31 - 35", "data": 1270},{"year": "2024", "q": "2024-03", "category": "56 - 60", "data": 728},{"year": "2024", "q": "2024-03", "category": "46 - 50", "data": 1594},{"year": "2024", "q": "2024-03", "category": "61 - 65", "data": 373},{"year": "2024", "q": "2024-03", "category": "36 - 40", "data": 1519},{"year": "2024", "q": "2024-02", "category": "36 - 40", "data": 1522},{"year": "2024", "q": "2024-02", "category": "51 - 55", "data": 1259},{"year": "2024", "q": "2024-02", "category": "46 - 50", "data": 1595},{"year": "2024", "q": "2024-02", "category": "61 - 65", "data": 386},{"year": "2024", "q": "2024-02", "category": "> 65", "data": 19},{"year": "2024", "q": "2024-02", "category": "56 - 60", "data": 732},{"year": "2024", "q": "2024-02", "category": "26 - 30", "data": 698},{"year": "2024", "q": "2024-02", "category": "41 - 45", "data": 1731},{"year": "2024", "q": "2024-02", "category": "25-", "data": 315},{"year": "2024", "q": "2024-02", "category": "31 - 35", "data": 1276},{"year": "2024", "q": "2024-01", "category": "41 - 45", "data": 1735},{"year": "2024", "q": "2024-01", "category": "46 - 50", "data": 1594},{"year": "2024", "q": "2024-01", "category": "25-", "data": 320},{"year": "2024", "q": "2024-01", "category": "61 - 65", "data": 401},{"year": "2024", "q": "2024-01", "category": "31 - 35", "data": 1276},{"year": "2024", "q": "2024-01", "category": "26 - 30", "data": 697},{"year": "2024", "q": "2024-01", "category": "36 - 40", "data": 1524},{"year": "2024", "q": "2024-01", "category": "> 65", "data": 19},{"year": "2024", "q": "2024-01", "category": "51 - 55", "data": 1259},{"year": "2024", "q": "2024-01", "category": "56 - 60", "data": 735},{"year": "2023", "q": "2023-12", "category": "31 - 35", "data": 1271},{"year": "2023", "q": "2023-12", "category": "51 - 55", "data": 1256},{"year": "2023", "q": "2023-12", "category": "36 - 40", "data": 1524},{"year": "2023", "q": "2023-12", "category": "56 - 60", "data": 738},{"year": "2023", "q": "2023-12", "category": "26 - 30", "data": 687},{"year": "2023", "q": "2023-12", "category": "41 - 45", "data": 1726},{"year": "2023", "q": "2023-12", "category": "46 - 50", "data": 1592},{"year": "2023", "q": "2023-12", "category": "25-", "data": 308},{"year": "2023", "q": "2023-12", "category": "61 - 65", "data": 418},{"year": "2023", "q": "2023-12", "category": "> 65", "data": 21},{"year": "2023", "q": "2023-11", "category": "25-", "data": 305},{"year": "2023", "q": "2023-11", "category": "41 - 45", "data": 1732},{"year": "2023", "q": "2023-11", "category": "46 - 50", "data": 1586},{"year": "2023", "q": "2023-11", "category": "36 - 40", "data": 1526},{"year": "2023", "q": "2023-11", "category": "56 - 60", "data": 740},{"year": "2023", "q": "2023-11", "category": "26 - 30", "data": 690},{"year": "2023", "q": "2023-11", "category": "61 - 65", "data": 426},{"year": "2023", "q": "2023-11", "category": "51 - 55", "data": 1255},{"year": "2023", "q": "2023-11", "category": "> 65", "data": 22},{"year": "2023", "q": "2023-11", "category": "31 - 35", "data": 1270},{"year": "2023", "q": "2023-10", "category": "36 - 40", "data": 1526},{"year": "2023", "q": "2023-10", "category": "51 - 55", "data": 1254},{"year": "2023", "q": "2023-10", "category": "56 - 60", "data": 741},{"year": "2023", "q": "2023-10", "category": "61 - 65", "data": 433},{"year": "2023", "q": "2023-10", "category": "31 - 35", "data": 1269},{"year": "2023", "q": "2023-10", "category": "26 - 30", "data": 685},{"year": "2023", "q": "2023-10", "category": "46 - 50", "data": 1588},{"year": "2023", "q": "2023-10", "category": "> 65", "data": 21},{"year": "2023", "q": "2023-10", "category": "41 - 45", "data": 1728},{"year": "2023", "q": "2023-10", "category": "25-", "data": 292},{"year": "2023", "q": "2023-09", "category": "46 - 50", "data": 1588},{"year": "2023", "q": "2023-09", "category": "25-", "data": 284},{"year": "2023", "q": "2023-09", "category": "56 - 60", "data": 749},{"year": "2023", "q": "2023-09", "category": "31 - 35", "data": 1269},{"year": "2023", "q": "2023-09", "category": "36 - 40", "data": 1524},{"year": "2023", "q": "2023-09", "category": "51 - 55", "data": 1256},{"year": "2023", "q": "2023-09", "category": "41 - 45", "data": 1728},{"year": "2023", "q": "2023-09", "category": "61 - 65", "data": 441},{"year": "2023", "q": "2023-09", "category": "> 65", "data": 23},{"year": "2023", "q": "2023-09", "category": "26 - 30", "data": 684},{"year": "2023", "q": "2023-08", "category": "46 - 50", "data": 1572},{"year": "2023", "q": "2023-08", "category": "25-", "data": 266},{"year": "2023", "q": "2023-08", "category": "61 - 65", "data": 458},{"year": "2023", "q": "2023-08", "category": "26 - 30", "data": 679},{"year": "2023", "q": "2023-08", "category": "31 - 35", "data": 1252},{"year": "2023", "q": "2023-08", "category": "36 - 40", "data": 1517},{"year": "2023", "q": "2023-08", "category": "51 - 55", "data": 1256},{"year": "2023", "q": "2023-08", "category": "56 - 60", "data": 752},{"year": "2023", "q": "2023-08", "category": "> 65", "data": 25},{"year": "2023", "q": "2023-08", "category": "41 - 45", "data": 1713},{"year": "2023", "q": "2023-07", "category": "51 - 55", "data": 1255},{"year": "2023", "q": "2023-07", "category": "56 - 60", "data": 752},{"year": "2023", "q": "2023-07", "category": "25-", "data": 256},{"year": "2023", "q": "2023-07", "category": "31 - 35", "data": 1249},{"year": "2023", "q": "2023-07", "category": "26 - 30", "data": 666},{"year": "2023", "q": "2023-07", "category": "41 - 45", "data": 1691},{"year": "2023", "q": "2023-07", "category": "> 65", "data": 26},{"year": "2023", "q": "2023-07", "category": "36 - 40", "data": 1502},{"year": "2023", "q": "2023-07", "category": "46 - 50", "data": 1568},{"year": "2023", "q": "2023-07", "category": "61 - 65", "data": 463},{"year": "2023", "q": "2023-06", "category": "41 - 45", "data": 1718},{"year": "2023", "q": "2023-06", "category": "25-", "data": 255},{"year": "2023", "q": "2023-06", "category": "61 - 65", "data": 478},{"year": "2023", "q": "2023-06", "category": "> 65", "data": 28},{"year": "2023", "q": "2023-06", "category": "36 - 40", "data": 1523},{"year": "2023", "q": "2023-06", "category": "56 - 60", "data": 753},{"year": "2023", "q": "2023-06", "category": "26 - 30", "data": 663},{"year": "2023", "q": "2023-06", "category": "46 - 50", "data": 1573},{"year": "2023", "q": "2023-06", "category": "31 - 35", "data": 1253},{"year": "2023", "q": "2023-06", "category": "51 - 55", "data": 1257},{"year": "2023", "q": "2023-05", "category": "51 - 55", "data": 1256},{"year": "2023", "q": "2023-05", "category": "26 - 30", "data": 656},{"year": "2023", "q": "2023-05", "category": "41 - 45", "data": 1714},{"year": "2023", "q": "2023-05", "category": "61 - 65", "data": 490},{"year": "2023", "q": "2023-05", "category": "31 - 35", "data": 1251},{"year": "2023", "q": "2023-05", "category": "36 - 40", "data": 1523},{"year": "2023", "q": "2023-05", "category": "56 - 60", "data": 753},{"year": "2023", "q": "2023-05", "category": "46 - 50", "data": 1579},{"year": "2023", "q": "2023-05", "category": "25-", "data": 252},{"year": "2023", "q": "2023-05", "category": "> 65", "data": 27},{"year": "2023", "q": "2023-04", "category": "26 - 30", "data": 646},{"year": "2023", "q": "2023-04", "category": "41 - 45", "data": 1709},{"year": "2023", "q": "2023-04", "category": "46 - 50", "data": 1577},{"year": "2023", "q": "2023-04", "category": "25-", "data": 249},{"year": "2023", "q": "2023-04", "category": "61 - 65", "data": 528},{"year": "2023", "q": "2023-04", "category": "51 - 55", "data": 1251},{"year": "2023", "q": "2023-04", "category": "56 - 60", "data": 753},{"year": "2023", "q": "2023-04", "category": "> 65", "data": 31},{"year": "2023", "q": "2023-04", "category": "31 - 35", "data": 1243},{"year": "2023", "q": "2023-04", "category": "36 - 40", "data": 1522},{"year": "2023", "q": "2023-03", "category": "31 - 35", "data": 1241},{"year": "2023", "q": "2023-03", "category": "51 - 55", "data": 1253},{"year": "2023", "q": "2023-03", "category": "26 - 30", "data": 637},{"year": "2023", "q": "2023-03", "category": "41 - 45", "data": 1702},{"year": "2023", "q": "2023-03", "category": "25-", "data": 244},{"year": "2023", "q": "2023-03", "category": "61 - 65", "data": 547},{"year": "2023", "q": "2023-03", "category": "> 65", "data": 32},{"year": "2023", "q": "2023-03", "category": "36 - 40", "data": 1518},{"year": "2023", "q": "2023-03", "category": "56 - 60", "data": 752},{"year": "2023", "q": "2023-03", "category": "46 - 50", "data": 1572},{"year": "2023", "q": "2023-02", "category": "25-", "data": 241},{"year": "2023", "q": "2023-02", "category": "36 - 40", "data": 1519},{"year": "2023", "q": "2023-02", "category": "56 - 60", "data": 749},{"year": "2023", "q": "2023-02", "category": "41 - 45", "data": 1701},{"year": "2023", "q": "2023-02", "category": "46 - 50", "data": 1570},{"year": "2023", "q": "2023-02", "category": "61 - 65", "data": 562},{"year": "2023", "q": "2023-02", "category": "> 65", "data": 36},{"year": "2023", "q": "2023-02", "category": "31 - 35", "data": 1237},{"year": "2023", "q": "2023-02", "category": "51 - 55", "data": 1250},{"year": "2023", "q": "2023-02", "category": "26 - 30", "data": 631},{"year": "2023", "q": "2023-01", "category": "36 - 40", "data": 1517},{"year": "2023", "q": "2023-01", "category": "41 - 45", "data": 1703},{"year": "2023", "q": "2023-01", "category": "25-", "data": 236},{"year": "2023", "q": "2023-01", "category": "61 - 65", "data": 579},{"year": "2023", "q": "2023-01", "category": "> 65", "data": 38},{"year": "2023", "q": "2023-01", "category": "51 - 55", "data": 1251},{"year": "2023", "q": "2023-01", "category": "56 - 60", "data": 748},{"year": "2023", "q": "2023-01", "category": "26 - 30", "data": 625},{"year": "2023", "q": "2023-01", "category": "31 - 35", "data": 1235},{"year": "2023", "q": "2023-01", "category": "46 - 50", "data": 1575},{"year": "2022", "q": "2022-12", "category": "26 - 30", "data": 618},{"year": "2022", "q": "2022-12", "category": "25-", "data": 229},{"year": "2022", "q": "2022-12", "category": "> 65", "data": 43},{"year": "2022", "q": "2022-12", "category": "31 - 35", "data": 1229},{"year": "2022", "q": "2022-12", "category": "56 - 60", "data": 748},{"year": "2022", "q": "2022-12", "category": "41 - 45", "data": 1698},{"year": "2022", "q": "2022-12", "category": "61 - 65", "data": 636},{"year": "2022", "q": "2022-12", "category": "51 - 55", "data": 1243},{"year": "2022", "q": "2022-12", "category": "46 - 50", "data": 1578},{"year": "2022", "q": "2022-12", "category": "36 - 40", "data": 1512},{"year": "2022", "q": "2022-11", "category": "36 - 40", "data": 1513},{"year": "2022", "q": "2022-11", "category": "51 - 55", "data": 1246},{"year": "2022", "q": "2022-11", "category": "56 - 60", "data": 750},{"year": "2022", "q": "2022-11", "category": "26 - 30", "data": 613},{"year": "2022", "q": "2022-11", "category": "> 65", "data": 47},{"year": "2022", "q": "2022-11", "category": "31 - 35", "data": 1229},{"year": "2022", "q": "2022-11", "category": "41 - 45", "data": 1698},{"year": "2022", "q": "2022-11", "category": "46 - 50", "data": 1579},{"year": "2022", "q": "2022-11", "category": "25-", "data": 225},{"year": "2022", "q": "2022-11", "category": "61 - 65", "data": 656},{"year": "2022", "q": "2022-10", "category": "61 - 65", "data": 690},{"year": "2022", "q": "2022-10", "category": "31 - 35", "data": 1223},{"year": "2022", "q": "2022-10", "category": "46 - 50", "data": 1576},{"year": "2022", "q": "2022-10", "category": "25-", "data": 214},{"year": "2022", "q": "2022-10", "category": "> 65", "data": 56},{"year": "2022", "q": "2022-10", "category": "36 - 40", "data": 1506},{"year": "2022", "q": "2022-10", "category": "51 - 55", "data": 1245},{"year": "2022", "q": "2022-10", "category": "56 - 60", "data": 753},{"year": "2022", "q": "2022-10", "category": "26 - 30", "data": 604},{"year": "2022", "q": "2022-10", "category": "41 - 45", "data": 1684},{"year": "2022", "q": "2022-09", "category": "51 - 55", "data": 1246},{"year": "2022", "q": "2022-09", "category": "56 - 60", "data": 752},{"year": "2022", "q": "2022-09", "category": "26 - 30", "data": 607},{"year": "2022", "q": "2022-09", "category": "25-", "data": 207},{"year": "2022", "q": "2022-09", "category": "61 - 65", "data": 705},{"year": "2022", "q": "2022-09", "category": "36 - 40", "data": 1505},{"year": "2022", "q": "2022-09", "category": "41 - 45", "data": 1679},{"year": "2022", "q": "2022-09", "category": "46 - 50", "data": 1581},{"year": "2022", "q": "2022-09", "category": "31 - 35", "data": 1225},{"year": "2022", "q": "2022-09", "category": "> 65", "data": 61},{"year": "2022", "q": "2022-08", "category": "26 - 30", "data": 587},{"year": "2022", "q": "2022-08", "category": "> 65", "data": 66},{"year": "2022", "q": "2022-08", "category": "61 - 65", "data": 733},{"year": "2022", "q": "2022-08", "category": "31 - 35", "data": 1218},{"year": "2022", "q": "2022-08", "category": "51 - 55", "data": 1242},{"year": "2022", "q": "2022-08", "category": "56 - 60", "data": 749},{"year": "2022", "q": "2022-08", "category": "41 - 45", "data": 1669},{"year": "2022", "q": "2022-08", "category": "25-", "data": 188},{"year": "2022", "q": "2022-08", "category": "46 - 50", "data": 1575},{"year": "2022", "q": "2022-08", "category": "36 - 40", "data": 1510},{"year": "2022", "q": "2022-07", "category": "25-", "data": 173},{"year": "2022", "q": "2022-07", "category": "56 - 60", "data": 748},{"year": "2022", "q": "2022-07", "category": "26 - 30", "data": 565},{"year": "2022", "q": "2022-07", "category": "46 - 50", "data": 1564},{"year": "2022", "q": "2022-07", "category": "36 - 40", "data": 1486},{"year": "2022", "q": "2022-07", "category": "41 - 45", "data": 1657},{"year": "2022", "q": "2022-07", "category": "61 - 65", "data": 761},{"year": "2022", "q": "2022-07", "category": "> 65", "data": 70},{"year": "2022", "q": "2022-07", "category": "31 - 35", "data": 1202},{"year": "2022", "q": "2022-07", "category": "51 - 55", "data": 1232},{"year": "2022", "q": "2022-06", "category": "56 - 60", "data": 751},{"year": "2022", "q": "2022-06", "category": "> 65", "data": 74},{"year": "2022", "q": "2022-06", "category": "25-", "data": 172},{"year": "2022", "q": "2022-06", "category": "46 - 50", "data": 1576},{"year": "2022", "q": "2022-06", "category": "61 - 65", "data": 786},{"year": "2022", "q": "2022-06", "category": "36 - 40", "data": 1495},{"year": "2022", "q": "2022-06", "category": "51 - 55", "data": 1234},{"year": "2022", "q": "2022-06", "category": "26 - 30", "data": 560},{"year": "2022", "q": "2022-06", "category": "41 - 45", "data": 1676},{"year": "2022", "q": "2022-06", "category": "31 - 35", "data": 1205},{"year": "2022", "q": "2022-05", "category": "61 - 65", "data": 827},{"year": "2022", "q": "2022-05", "category": "> 65", "data": 77},{"year": "2022", "q": "2022-05", "category": "36 - 40", "data": 1488},{"year": "2022", "q": "2022-05", "category": "56 - 60", "data": 751},{"year": "2022", "q": "2022-05", "category": "26 - 30", "data": 541},{"year": "2022", "q": "2022-05", "category": "46 - 50", "data": 1576},{"year": "2022", "q": "2022-05", "category": "25-", "data": 161},{"year": "2022", "q": "2022-05", "category": "51 - 55", "data": 1229},{"year": "2022", "q": "2022-05", "category": "41 - 45", "data": 1665},{"year": "2022", "q": "2022-05", "category": "31 - 35", "data": 1195},{"year": "2022", "q": "2022-04", "category": "36 - 40", "data": 1482},{"year": "2022", "q": "2022-04", "category": "51 - 55", "data": 1233},{"year": "2022", "q": "2022-04", "category": "56 - 60", "data": 752},{"year": "2022", "q": "2022-04", "category": "26 - 30", "data": 530},{"year": "2022", "q": "2022-04", "category": "46 - 50", "data": 1573},{"year": "2022", "q": "2022-04", "category": "61 - 65", "data": 891},{"year": "2022", "q": "2022-04", "category": "25-", "data": 159},{"year": "2022", "q": "2022-04", "category": "> 65", "data": 80},{"year": "2022", "q": "2022-04", "category": "31 - 35", "data": 1196},{"year": "2022", "q": "2022-04", "category": "41 - 45", "data": 1670},{"year": "2022", "q": "2022-03", "category": "56 - 60", "data": 751},{"year": "2022", "q": "2022-03", "category": "46 - 50", "data": 1574},{"year": "2022", "q": "2022-03", "category": "> 65", "data": 82},{"year": "2022", "q": "2022-03", "category": "36 - 40", "data": 1484},{"year": "2022", "q": "2022-03", "category": "51 - 55", "data": 1230},{"year": "2022", "q": "2022-03", "category": "26 - 30", "data": 516},{"year": "2022", "q": "2022-03", "category": "41 - 45", "data": 1669},{"year": "2022", "q": "2022-03", "category": "25-", "data": 151},{"year": "2022", "q": "2022-03", "category": "61 - 65", "data": 914},{"year": "2022", "q": "2022-03", "category": "31 - 35", "data": 1190},{"year": "2022", "q": "2022-02", "category": "51 - 55", "data": 1231},{"year": "2022", "q": "2022-02", "category": "56 - 60", "data": 749},{"year": "2022", "q": "2022-02", "category": "25-", "data": 151},{"year": "2022", "q": "2022-02", "category": "31 - 35", "data": 1185},{"year": "2022", "q": "2022-02", "category": "26 - 30", "data": 512},{"year": "2022", "q": "2022-02", "category": "41 - 45", "data": 1673},{"year": "2022", "q": "2022-02", "category": "36 - 40", "data": 1473},{"year": "2022", "q": "2022-02", "category": "46 - 50", "data": 1568},{"year": "2022", "q": "2022-02", "category": "61 - 65", "data": 951},{"year": "2022", "q": "2022-02", "category": "> 65", "data": 90},{"year": "2022", "q": "2022-01", "category": "46 - 50", "data": 1563},{"year": "2022", "q": "2022-01", "category": "> 65", "data": 93},{"year": "2022", "q": "2022-01", "category": "51 - 55", "data": 1232},{"year": "2022", "q": "2022-01", "category": "26 - 30", "data": 503},{"year": "2022", "q": "2022-01", "category": "41 - 45", "data": 1674},{"year": "2022", "q": "2022-01", "category": "61 - 65", "data": 984},{"year": "2022", "q": "2022-01", "category": "31 - 35", "data": 1185},{"year": "2022", "q": "2022-01", "category": "56 - 60", "data": 750},{"year": "2022", "q": "2022-01", "category": "25-", "data": 147},{"year": "2022", "q": "2022-01", "category": "36 - 40", "data": 1472},{"year": "2021", "q": "2021-12", "category": "51 - 55", "data": 1234},{"year": "2021", "q": "2021-12", "category": "56 - 60", "data": 750},{"year": "2021", "q": "2021-12", "category": "26 - 30", "data": 497},{"year": "2021", "q": "2021-12", "category": "41 - 45", "data": 1662},{"year": "2021", "q": "2021-12", "category": "> 65", "data": 101},{"year": "2021", "q": "2021-12", "category": "46 - 50", "data": 1549},{"year": "2021", "q": "2021-12", "category": "25-", "data": 135},{"year": "2021", "q": "2021-12", "category": "61 - 65", "data": 1062},{"year": "2021", "q": "2021-12", "category": "31 - 35", "data": 1172},{"year": "2021", "q": "2021-12", "category": "36 - 40", "data": 1461},{"year": "2021", "q": "2021-11", "category": "26 - 30", "data": 499},{"year": "2021", "q": "2021-11", "category": "25-", "data": 130},{"year": "2021", "q": "2021-11", "category": "61 - 65", "data": 1093},{"year": "2021", "q": "2021-11", "category": "36 - 40", "data": 1461},{"year": "2021", "q": "2021-11", "category": "51 - 55", "data": 1234},{"year": "2021", "q": "2021-11", "category": "41 - 45", "data": 1663},{"year": "2021", "q": "2021-11", "category": "46 - 50", "data": 1546},{"year": "2021", "q": "2021-11", "category": "31 - 35", "data": 1172},{"year": "2021", "q": "2021-11", "category": "> 65", "data": 103},{"year": "2021", "q": "2021-11", "category": "56 - 60", "data": 752},{"year": "2021", "q": "2021-10", "category": "46 - 50", "data": 1547},{"year": "2021", "q": "2021-10", "category": "31 - 35", "data": 1161},{"year": "2021", "q": "2021-10", "category": "56 - 60", "data": 754},{"year": "2021", "q": "2021-10", "category": "25-", "data": 118},{"year": "2021", "q": "2021-10", "category": "41 - 45", "data": 1658},{"year": "2021", "q": "2021-10", "category": "36 - 40", "data": 1456},{"year": "2021", "q": "2021-10", "category": "51 - 55", "data": 1230},{"year": "2021", "q": "2021-10", "category": "26 - 30", "data": 500},{"year": "2021", "q": "2021-10", "category": "> 65", "data": 106},{"year": "2021", "q": "2021-10", "category": "61 - 65", "data": 1119},{"year": "2021", "q": "2021-09", "category": "31 - 35", "data": 1168},{"year": "2021", "q": "2021-09", "category": "56 - 60", "data": 756},{"year": "2021", "q": "2021-09", "category": "41 - 45", "data": 1660},{"year": "2021", "q": "2021-09", "category": "61 - 65", "data": 1152},{"year": "2021", "q": "2021-09", "category": "36 - 40", "data": 1458},{"year": "2021", "q": "2021-09", "category": "51 - 55", "data": 1230},{"year": "2021", "q": "2021-09", "category": "26 - 30", "data": 489},{"year": "2021", "q": "2021-09", "category": "46 - 50", "data": 1544},{"year": "2021", "q": "2021-09", "category": "> 65", "data": 112},{"year": "2021", "q": "2021-09", "category": "25-", "data": 108},{"year": "2021", "q": "2021-08", "category": "46 - 50", "data": 1542},{"year": "2021", "q": "2021-08", "category": "25-", "data": 100},{"year": "2021", "q": "2021-08", "category": "> 65", "data": 114},{"year": "2021", "q": "2021-08", "category": "31 - 35", "data": 1162},{"year": "2021", "q": "2021-08", "category": "41 - 45", "data": 1648},{"year": "2021", "q": "2021-08", "category": "61 - 65", "data": 1188},{"year": "2021", "q": "2021-08", "category": "51 - 55", "data": 1232},{"year": "2021", "q": "2021-08", "category": "26 - 30", "data": 476},{"year": "2021", "q": "2021-08", "category": "36 - 40", "data": 1452},{"year": "2021", "q": "2021-08", "category": "56 - 60", "data": 754},{"year": "2021", "q": "2021-07", "category": "51 - 55", "data": 1232},{"year": "2021", "q": "2021-07", "category": "26 - 30", "data": 464},{"year": "2021", "q": "2021-07", "category": "41 - 45", "data": 1637},{"year": "2021", "q": "2021-07", "category": "25-", "data": 96},{"year": "2021", "q": "2021-07", "category": "> 65", "data": 121},{"year": "2021", "q": "2021-07", "category": "56 - 60", "data": 758},{"year": "2021", "q": "2021-07", "category": "46 - 50", "data": 1532},{"year": "2021", "q": "2021-07", "category": "31 - 35", "data": 1158},{"year": "2021", "q": "2021-07", "category": "61 - 65", "data": 1220},{"year": "2021", "q": "2021-07", "category": "36 - 40", "data": 1446},{"year": "2021", "q": "2021-06", "category": "31 - 35", "data": 1163},{"year": "2021", "q": "2021-06", "category": "25-", "data": 96},{"year": "2021", "q": "2021-06", "category": "36 - 40", "data": 1455},{"year": "2021", "q": "2021-06", "category": "51 - 55", "data": 1238},{"year": "2021", "q": "2021-06", "category": "56 - 60", "data": 760},{"year": "2021", "q": "2021-06", "category": "41 - 45", "data": 1646},{"year": "2021", "q": "2021-06", "category": "> 65", "data": 128},{"year": "2021", "q": "2021-06", "category": "26 - 30", "data": 464},{"year": "2021", "q": "2021-06", "category": "46 - 50", "data": 1547},{"year": "2021", "q": "2021-06", "category": "61 - 65", "data": 1253},{"year": "2021", "q": "2021-05", "category": "61 - 65", "data": 1282},{"year": "2021", "q": "2021-05", "category": "31 - 35", "data": 1160},{"year": "2021", "q": "2021-05", "category": "26 - 30", "data": 467},{"year": "2021", "q": "2021-05", "category": "41 - 45", "data": 1648},{"year": "2021", "q": "2021-05", "category": "25-", "data": 96},{"year": "2021", "q": "2021-05", "category": "51 - 55", "data": 1239},{"year": "2021", "q": "2021-05", "category": "56 - 60", "data": 762},{"year": "2021", "q": "2021-05", "category": "46 - 50", "data": 1551},{"year": "2021", "q": "2021-05", "category": "> 65", "data": 132},{"year": "2021", "q": "2021-05", "category": "36 - 40", "data": 1455},{"year": "2021", "q": "2021-04", "category": "26 - 30", "data": 460},{"year": "2021", "q": "2021-04", "category": "25-", "data": 97},{"year": "2021", "q": "2021-04", "category": "> 65", "data": 144},{"year": "2021", "q": "2021-04", "category": "31 - 35", "data": 1161},{"year": "2021", "q": "2021-04", "category": "51 - 55", "data": 1236},{"year": "2021", "q": "2021-04", "category": "41 - 45", "data": 1649},{"year": "2021", "q": "2021-04", "category": "46 - 50", "data": 1550},{"year": "2021", "q": "2021-04", "category": "56 - 60", "data": 765},{"year": "2021", "q": "2021-04", "category": "61 - 65", "data": 1373},{"year": "2021", "q": "2021-04", "category": "36 - 40", "data": 1448},{"year": "2021", "q": "2021-03", "category": "31 - 35", "data": 1164},{"year": "2021", "q": "2021-03", "category": "36 - 40", "data": 1446},{"year": "2021", "q": "2021-03", "category": "25-", "data": 96},{"year": "2021", "q": "2021-03", "category": "41 - 45", "data": 1644},{"year": "2021", "q": "2021-03", "category": "46 - 50", "data": 1554},{"year": "2021", "q": "2021-03", "category": "61 - 65", "data": 1399},{"year": "2021", "q": "2021-03", "category": "51 - 55", "data": 1239},{"year": "2021", "q": "2021-03", "category": "56 - 60", "data": 764},{"year": "2021", "q": "2021-03", "category": "26 - 30", "data": 457},{"year": "2021", "q": "2021-03", "category": "> 65", "data": 149},{"year": "2021", "q": "2021-02", "category": "51 - 55", "data": 1237},{"year": "2021", "q": "2021-02", "category": "56 - 60", "data": 765},{"year": "2021", "q": "2021-02", "category": "61 - 65", "data": 1429},{"year": "2021", "q": "2021-02", "category": "41 - 45", "data": 1644},{"year": "2021", "q": "2021-02", "category": "31 - 35", "data": 1161},{"year": "2021", "q": "2021-02", "category": "36 - 40", "data": 1452},{"year": "2021", "q": "2021-02", "category": "26 - 30", "data": 447},{"year": "2021", "q": "2021-02", "category": "46 - 50", "data": 1554},{"year": "2021", "q": "2021-02", "category": "25-", "data": 91},{"year": "2021", "q": "2021-02", "category": "> 65", "data": 151},{"year": "2021", "q": "2021-01", "category": "> 65", "data": 158},{"year": "2021", "q": "2021-01", "category": "36 - 40", "data": 1450},{"year": "2021", "q": "2021-01", "category": "51 - 55", "data": 1238},{"year": "2021", "q": "2021-01", "category": "26 - 30", "data": 433},{"year": "2021", "q": "2021-01", "category": "46 - 50", "data": 1551},{"year": "2021", "q": "2021-01", "category": "31 - 35", "data": 1160},{"year": "2021", "q": "2021-01", "category": "56 - 60", "data": 762},{"year": "2021", "q": "2021-01", "category": "25-", "data": 88},{"year": "2021", "q": "2021-01", "category": "41 - 45", "data": 1645},{"year": "2021", "q": "2021-01", "category": "61 - 65", "data": 1502},{"year": "2020", "q": "2020-12", "category": "26 - 30", "data": 421},{"year": "2020", "q": "2020-12", "category": "51 - 55", "data": 1235},{"year": "2020", "q": "2020-12", "category": "56 - 60", "data": 759},{"year": "2020", "q": "2020-12", "category": "> 65", "data": 170},{"year": "2020", "q": "2020-12", "category": "46 - 50", "data": 1551},{"year": "2020", "q": "2020-12", "category": "31 - 35", "data": 1154},{"year": "2020", "q": "2020-12", "category": "41 - 45", "data": 1635},{"year": "2020", "q": "2020-12", "category": "36 - 40", "data": 1446},{"year": "2020", "q": "2020-12", "category": "61 - 65", "data": 1593},{"year": "2020", "q": "2020-12", "category": "25-", "data": 84},{"year": "2020", "q": "2020-11", "category": "36 - 40", "data": 1442},{"year": "2020", "q": "2020-11", "category": "31 - 35", "data": 1153},{"year": "2020", "q": "2020-11", "category": "51 - 55", "data": 1236},{"year": "2020", "q": "2020-11", "category": "46 - 50", "data": 1551},{"year": "2020", "q": "2020-11", "category": "61 - 65", "data": 1618},{"year": "2020", "q": "2020-11", "category": "> 65", "data": 174},{"year": "2020", "q": "2020-11", "category": "56 - 60", "data": 760},{"year": "2020", "q": "2020-11", "category": "26 - 30", "data": 422},{"year": "2020", "q": "2020-11", "category": "41 - 45", "data": 1635},{"year": "2020", "q": "2020-11", "category": "25-", "data": 82},{"year": "2020", "q": "2020-10", "category": "61 - 65", "data": 1647},{"year": "2020", "q": "2020-10", "category": "36 - 40", "data": 1433},{"year": "2020", "q": "2020-10", "category": "51 - 55", "data": 1237},{"year": "2020", "q": "2020-10", "category": "46 - 50", "data": 1547},{"year": "2020", "q": "2020-10", "category": "31 - 35", "data": 1137},{"year": "2020", "q": "2020-10", "category": "56 - 60", "data": 757},{"year": "2020", "q": "2020-10", "category": "41 - 45", "data": 1628},{"year": "2020", "q": "2020-10", "category": "25-", "data": 73},{"year": "2020", "q": "2020-10", "category": "> 65", "data": 177},{"year": "2020", "q": "2020-10", "category": "26 - 30", "data": 404},{"year": "2020", "q": "2020-09", "category": "41 - 45", "data": 1616},{"year": "2020", "q": "2020-09", "category": "36 - 40", "data": 1420},{"year": "2020", "q": "2020-09", "category": "26 - 30", "data": 384},{"year": "2020", "q": "2020-09", "category": "46 - 50", "data": 1541},{"year": "2020", "q": "2020-09", "category": "61 - 65", "data": 1671},{"year": "2020", "q": "2020-09", "category": "> 65", "data": 179},{"year": "2020", "q": "2020-09", "category": "56 - 60", "data": 755},{"year": "2020", "q": "2020-09", "category": "25-", "data": 61},{"year": "2020", "q": "2020-09", "category": "31 - 35", "data": 1116},{"year": "2020", "q": "2020-09", "category": "51 - 55", "data": 1232},{"year": "2020", "q": "2020-08", "category": "26 - 30", "data": 363},{"year": "2020", "q": "2020-08", "category": "41 - 45", "data": 1611},{"year": "2020", "q": "2020-08", "category": "46 - 50", "data": 1526},{"year": "2020", "q": "2020-08", "category": "25-", "data": 60},{"year": "2020", "q": "2020-08", "category": "61 - 65", "data": 1707},{"year": "2020", "q": "2020-08", "category": "> 65", "data": 190},{"year": "2020", "q": "2020-08", "category": "51 - 55", "data": 1222},{"year": "2020", "q": "2020-08", "category": "56 - 60", "data": 752},{"year": "2020", "q": "2020-08", "category": "31 - 35", "data": 1098},{"year": "2020", "q": "2020-08", "category": "36 - 40", "data": 1398},{"year": "2020", "q": "2020-07", "category": "41 - 45", "data": 1604},{"year": "2020", "q": "2020-07", "category": "61 - 65", "data": 1742},{"year": "2020", "q": "2020-07", "category": "31 - 35", "data": 1088},{"year": "2020", "q": "2020-07", "category": "51 - 55", "data": 1217},{"year": "2020", "q": "2020-07", "category": "26 - 30", "data": 362},{"year": "2020", "q": "2020-07", "category": "25-", "data": 49},{"year": "2020", "q": "2020-07", "category": "> 65", "data": 198},{"year": "2020", "q": "2020-07", "category": "46 - 50", "data": 1518},{"year": "2020", "q": "2020-07", "category": "36 - 40", "data": 1392},{"year": "2020", "q": "2020-07", "category": "56 - 60", "data": 751},{"year": "2020", "q": "2020-06", "category": "26 - 30", "data": 355},{"year": "2020", "q": "2020-06", "category": "46 - 50", "data": 1533},{"year": "2020", "q": "2020-06", "category": "36 - 40", "data": 1397},{"year": "2020", "q": "2020-06", "category": "61 - 65", "data": 1795},{"year": "2020", "q": "2020-06", "category": "41 - 45", "data": 1616},{"year": "2020", "q": "2020-06", "category": "25-", "data": 48},{"year": "2020", "q": "2020-06", "category": "> 65", "data": 202},{"year": "2020", "q": "2020-06", "category": "31 - 35", "data": 1090},{"year": "2020", "q": "2020-06", "category": "51 - 55", "data": 1220},{"year": "2020", "q": "2020-06", "category": "56 - 60", "data": 754},{"year": "2020", "q": "2020-05", "category": "46 - 50", "data": 1531},{"year": "2020", "q": "2020-05", "category": "25-", "data": 47},{"year": "2020", "q": "2020-05", "category": "61 - 65", "data": 1828},{"year": "2020", "q": "2020-05", "category": "31 - 35", "data": 1085},{"year": "2020", "q": "2020-05", "category": "51 - 55", "data": 1219},{"year": "2020", "q": "2020-05", "category": "41 - 45", "data": 1613},{"year": "2020", "q": "2020-05", "category": "> 65", "data": 210},{"year": "2020", "q": "2020-05", "category": "36 - 40", "data": 1394},{"year": "2020", "q": "2020-05", "category": "56 - 60", "data": 756},{"year": "2020", "q": "2020-05", "category": "26 - 30", "data": 355},{"year": "2020", "q": "2020-04", "category": "> 65", "data": 235},{"year": "2020", "q": "2020-04", "category": "46 - 50", "data": 1529},{"year": "2020", "q": "2020-04", "category": "51 - 55", "data": 1214},{"year": "2020", "q": "2020-04", "category": "56 - 60", "data": 757},{"year": "2020", "q": "2020-04", "category": "41 - 45", "data": 1606},{"year": "2020", "q": "2020-04", "category": "61 - 65", "data": 1932},{"year": "2020", "q": "2020-04", "category": "31 - 35", "data": 1075},{"year": "2020", "q": "2020-04", "category": "36 - 40", "data": 1384},{"year": "2020", "q": "2020-04", "category": "26 - 30", "data": 353},{"year": "2020", "q": "2020-04", "category": "25-", "data": 46},{"year": "2020", "q": "2020-03", "category": "> 65", "data": 243},{"year": "2020", "q": "2020-03", "category": "31 - 35", "data": 1072},{"year": "2020", "q": "2020-03", "category": "26 - 30", "data": 348},{"year": "2020", "q": "2020-03", "category": "41 - 45", "data": 1606},{"year": "2020", "q": "2020-03", "category": "46 - 50", "data": 1525},{"year": "2020", "q": "2020-03", "category": "36 - 40", "data": 1383},{"year": "2020", "q": "2020-03", "category": "51 - 55", "data": 1213},{"year": "2020", "q": "2020-03", "category": "25-", "data": 45},{"year": "2020", "q": "2020-03", "category": "61 - 65", "data": 1956},{"year": "2020", "q": "2020-03", "category": "56 - 60", "data": 752},{"year": "2020", "q": "2020-02", "category": "25-", "data": 44},{"year": "2020", "q": "2020-02", "category": "> 65", "data": 249},{"year": "2020", "q": "2020-02", "category": "36 - 40", "data": 1384},{"year": "2020", "q": "2020-02", "category": "26 - 30", "data": 343},{"year": "2020", "q": "2020-02", "category": "46 - 50", "data": 1525},{"year": "2020", "q": "2020-02", "category": "61 - 65", "data": 2001},{"year": "2020", "q": "2020-02", "category": "31 - 35", "data": 1070},{"year": "2020", "q": "2020-02", "category": "56 - 60", "data": 757},{"year": "2020", "q": "2020-02", "category": "41 - 45", "data": 1606},{"year": "2020", "q": "2020-02", "category": "51 - 55", "data": 1217},{"year": "2020", "q": "2020-01", "category": "31 - 35", "data": 1062},{"year": "2020", "q": "2020-01", "category": "36 - 40", "data": 1383},{"year": "2020", "q": "2020-01", "category": "51 - 55", "data": 1216},{"year": "2020", "q": "2020-01", "category": "56 - 60", "data": 758},{"year": "2020", "q": "2020-01", "category": "46 - 50", "data": 1523},{"year": "2020", "q": "2020-01", "category": "26 - 30", "data": 340},{"year": "2020", "q": "2020-01", "category": "25-", "data": 45},{"year": "2020", "q": "2020-01", "category": "61 - 65", "data": 2063},{"year": "2020", "q": "2020-01", "category": "> 65", "data": 262},{"year": "2020", "q": "2020-01", "category": "41 - 45", "data": 1612},{"year": "2019", "q": "2019-12", "category": "26 - 30", "data": 333},{"year": "2019", "q": "2019-12", "category": "46 - 50", "data": 1519},{"year": "2019", "q": "2019-12", "category": "61 - 65", "data": 2111},{"year": "2019", "q": "2019-12", "category": "31 - 35", "data": 1055},{"year": "2019", "q": "2019-12", "category": "36 - 40", "data": 1381},{"year": "2019", "q": "2019-12", "category": "56 - 60", "data": 756},{"year": "2019", "q": "2019-12", "category": "> 65", "data": 284},{"year": "2019", "q": "2019-12", "category": "51 - 55", "data": 1212},{"year": "2019", "q": "2019-12", "category": "41 - 45", "data": 1611},{"year": "2019", "q": "2019-12", "category": "25-", "data": 41},{"year": "2019", "q": "2019-11", "category": "51 - 55", "data": 1217},{"year": "2019", "q": "2019-11", "category": "56 - 60", "data": 759},{"year": "2019", "q": "2019-11", "category": "41 - 45", "data": 1615},{"year": "2019", "q": "2019-11", "category": "25-", "data": 40},{"year": "2019", "q": "2019-11", "category": "36 - 40", "data": 1379},{"year": "2019", "q": "2019-11", "category": "26 - 30", "data": 330},{"year": "2019", "q": "2019-11", "category": "46 - 50", "data": 1521},{"year": "2019", "q": "2019-11", "category": "31 - 35", "data": 1051},{"year": "2019", "q": "2019-11", "category": "61 - 65", "data": 2140},{"year": "2019", "q": "2019-11", "category": "> 65", "data": 293},{"year": "2019", "q": "2019-10", "category": "36 - 40", "data": 1385},{"year": "2019", "q": "2019-10", "category": "51 - 55", "data": 1218},{"year": "2019", "q": "2019-10", "category": "26 - 30", "data": 327},{"year": "2019", "q": "2019-10", "category": "56 - 60", "data": 761},{"year": "2019", "q": "2019-10", "category": "41 - 45", "data": 1613},{"year": "2019", "q": "2019-10", "category": "61 - 65", "data": 2167},{"year": "2019", "q": "2019-10", "category": "> 65", "data": 298},{"year": "2019", "q": "2019-10", "category": "31 - 35", "data": 1050},{"year": "2019", "q": "2019-10", "category": "46 - 50", "data": 1522},{"year": "2019", "q": "2019-10", "category": "25-", "data": 36},{"year": "2019", "q": "2019-09", "category": "46 - 50", "data": 1525},{"year": "2019", "q": "2019-09", "category": "31 - 35", "data": 1039},{"year": "2019", "q": "2019-09", "category": "25-", "data": 34},{"year": "2019", "q": "2019-09", "category": "61 - 65", "data": 2200},{"year": "2019", "q": "2019-09", "category": "36 - 40", "data": 1377},{"year": "2019", "q": "2019-09", "category": "51 - 55", "data": 1215},{"year": "2019", "q": "2019-09", "category": "> 65", "data": 303},{"year": "2019", "q": "2019-09", "category": "56 - 60", "data": 760},{"year": "2019", "q": "2019-09", "category": "26 - 30", "data": 309},{"year": "2019", "q": "2019-09", "category": "41 - 45", "data": 1608},{"year": "2019", "q": "2019-08", "category": "41 - 45", "data": 1594},{"year": "2019", "q": "2019-08", "category": "25-", "data": 30},{"year": "2019", "q": "2019-08", "category": "61 - 65", "data": 2216},{"year": "2019", "q": "2019-08", "category": "31 - 35", "data": 1037},{"year": "2019", "q": "2019-08", "category": "36 - 40", "data": 1370},{"year": "2019", "q": "2019-08", "category": "46 - 50", "data": 1519},{"year": "2019", "q": "2019-08", "category": "56 - 60", "data": 758},{"year": "2019", "q": "2019-08", "category": "26 - 30", "data": 290},{"year": "2019", "q": "2019-08", "category": "> 65", "data": 323},{"year": "2019", "q": "2019-08", "category": "51 - 55", "data": 1210},{"year": "2019", "q": "2019-07", "category": "61 - 65", "data": 2240},{"year": "2019", "q": "2019-07", "category": "51 - 55", "data": 1206},{"year": "2019", "q": "2019-07", "category": "46 - 50", "data": 1508},{"year": "2019", "q": "2019-07", "category": "25-", "data": 23},{"year": "2019", "q": "2019-07", "category": "31 - 35", "data": 1028},{"year": "2019", "q": "2019-07", "category": "56 - 60", "data": 755},{"year": "2019", "q": "2019-07", "category": "26 - 30", "data": 278},{"year": "2019", "q": "2019-07", "category": "41 - 45", "data": 1569},{"year": "2019", "q": "2019-07", "category": "> 65", "data": 333},{"year": "2019", "q": "2019-07", "category": "36 - 40", "data": 1358},{"year": "2019", "q": "2019-06", "category": "61 - 65", "data": 2275},{"year": "2019", "q": "2019-06", "category": "31 - 35", "data": 1030},{"year": "2019", "q": "2019-06", "category": "36 - 40", "data": 1369},{"year": "2019", "q": "2019-06", "category": "26 - 30", "data": 276},{"year": "2019", "q": "2019-06", "category": "46 - 50", "data": 1521},{"year": "2019", "q": "2019-06", "category": "> 65", "data": 344},{"year": "2019", "q": "2019-06", "category": "51 - 55", "data": 1214},{"year": "2019", "q": "2019-06", "category": "41 - 45", "data": 1594},{"year": "2019", "q": "2019-06", "category": "25-", "data": 23},{"year": "2019", "q": "2019-06", "category": "56 - 60", "data": 755},{"year": "2019", "q": "2019-05", "category": "51 - 55", "data": 1218},{"year": "2019", "q": "2019-05", "category": "26 - 30", "data": 274},{"year": "2019", "q": "2019-05", "category": "31 - 35", "data": 1026},{"year": "2019", "q": "2019-05", "category": "36 - 40", "data": 1359},{"year": "2019", "q": "2019-05", "category": "56 - 60", "data": 755},{"year": "2019", "q": "2019-05", "category": "46 - 50", "data": 1523},{"year": "2019", "q": "2019-05", "category": "41 - 45", "data": 1594},{"year": "2019", "q": "2019-05", "category": "25-", "data": 23},{"year": "2019", "q": "2019-05", "category": "61 - 65", "data": 2304},{"year": "2019", "q": "2019-05", "category": "> 65", "data": 353},{"year": "2019", "q": "2019-04", "category": "41 - 45", "data": 1593},{"year": "2019", "q": "2019-04", "category": "> 65", "data": 374},{"year": "2019", "q": "2019-04", "category": "36 - 40", "data": 1355},{"year": "2019", "q": "2019-04", "category": "25-", "data": 24},{"year": "2019", "q": "2019-04", "category": "31 - 35", "data": 1019},{"year": "2019", "q": "2019-04", "category": "56 - 60", "data": 751},{"year": "2019", "q": "2019-04", "category": "26 - 30", "data": 273},{"year": "2019", "q": "2019-04", "category": "46 - 50", "data": 1521},{"year": "2019", "q": "2019-04", "category": "61 - 65", "data": 2345},{"year": "2019", "q": "2019-04", "category": "51 - 55", "data": 1213},{"year": "2019", "q": "2019-03", "category": "51 - 55", "data": 1212},{"year": "2019", "q": "2019-03", "category": "31 - 35", "data": 1002},{"year": "2019", "q": "2019-03", "category": "36 - 40", "data": 1344},{"year": "2019", "q": "2019-03", "category": "41 - 45", "data": 1586},{"year": "2019", "q": "2019-03", "category": "46 - 50", "data": 1519},{"year": "2019", "q": "2019-03", "category": "61 - 65", "data": 2363},{"year": "2019", "q": "2019-03", "category": "> 65", "data": 385},{"year": "2019", "q": "2019-03", "category": "56 - 60", "data": 749},{"year": "2019", "q": "2019-03", "category": "26 - 30", "data": 272},{"year": "2019", "q": "2019-03", "category": "25-", "data": 25},{"year": "2019", "q": "2019-02", "category": "25-", "data": 24},{"year": "2019", "q": "2019-02", "category": "> 65", "data": 395},{"year": "2019", "q": "2019-02", "category": "36 - 40", "data": 1346},{"year": "2019", "q": "2019-02", "category": "56 - 60", "data": 749},{"year": "2019", "q": "2019-02", "category": "26 - 30", "data": 271},{"year": "2019", "q": "2019-02", "category": "41 - 45", "data": 1580},{"year": "2019", "q": "2019-02", "category": "31 - 35", "data": 996},{"year": "2019", "q": "2019-02", "category": "46 - 50", "data": 1514},{"year": "2019", "q": "2019-02", "category": "61 - 65", "data": 2387},{"year": "2019", "q": "2019-02", "category": "51 - 55", "data": 1217},{"year": "2019", "q": "2019-01", "category": "41 - 45", "data": 1577},{"year": "2019", "q": "2019-01", "category": "46 - 50", "data": 1510},{"year": "2019", "q": "2019-01", "category": "25-", "data": 24},{"year": "2019", "q": "2019-01", "category": "26 - 30", "data": 263},{"year": "2019", "q": "2019-01", "category": "61 - 65", "data": 2415},{"year": "2019", "q": "2019-01", "category": "> 65", "data": 403},{"year": "2019", "q": "2019-01", "category": "36 - 40", "data": 1338},{"year": "2019", "q": "2019-01", "category": "51 - 55", "data": 1214},{"year": "2019", "q": "2019-01", "category": "56 - 60", "data": 751},{"year": "2019", "q": "2019-01", "category": "31 - 35", "data": 979},{"year": "2018", "q": "2018-12", "category": "41 - 45", "data": 1565},{"year": "2018", "q": "2018-12", "category": "36 - 40", "data": 1329},{"year": "2018", "q": "2018-12", "category": "51 - 55", "data": 1216},{"year": "2018", "q": "2018-12", "category": "26 - 30", "data": 254},{"year": "2018", "q": "2018-12", "category": "46 - 50", "data": 1502},{"year": "2018", "q": "2018-12", "category": "25-", "data": 23},{"year": "2018", "q": "2018-12", "category": "> 65", "data": 433},{"year": "2018", "q": "2018-12", "category": "31 - 35", "data": 960},{"year": "2018", "q": "2018-12", "category": "61 - 65", "data": 2450},{"year": "2018", "q": "2018-12", "category": "56 - 60", "data": 744},{"year": "2018", "q": "2018-11", "category": "36 - 40", "data": 1323},{"year": "2018", "q": "2018-11", "category": "51 - 55", "data": 1210},{"year": "2018", "q": "2018-11", "category": "25-", "data": 23},{"year": "2018", "q": "2018-11", "category": "> 65", "data": 446},{"year": "2018", "q": "2018-11", "category": "56 - 60", "data": 746},{"year": "2018", "q": "2018-11", "category": "61 - 65", "data": 2480},{"year": "2018", "q": "2018-11", "category": "31 - 35", "data": 946},{"year": "2018", "q": "2018-11", "category": "26 - 30", "data": 246},{"year": "2018", "q": "2018-11", "category": "41 - 45", "data": 1556},{"year": "2018", "q": "2018-11", "category": "46 - 50", "data": 1498},{"year": "2018", "q": "2018-10", "category": "46 - 50", "data": 1493},{"year": "2018", "q": "2018-10", "category": "> 65", "data": 456},{"year": "2018", "q": "2018-10", "category": "31 - 35", "data": 946},{"year": "2018", "q": "2018-10", "category": "56 - 60", "data": 746},{"year": "2018", "q": "2018-10", "category": "26 - 30", "data": 238},{"year": "2018", "q": "2018-10", "category": "41 - 45", "data": 1552},{"year": "2018", "q": "2018-10", "category": "25-", "data": 19},{"year": "2018", "q": "2018-10", "category": "61 - 65", "data": 2522},{"year": "2018", "q": "2018-10", "category": "36 - 40", "data": 1316},{"year": "2018", "q": "2018-10", "category": "51 - 55", "data": 1208},{"year": "2018", "q": "2018-09", "category": "46 - 50", "data": 1485},{"year": "2018", "q": "2018-09", "category": "25-", "data": 13},{"year": "2018", "q": "2018-09", "category": "61 - 65", "data": 2557},{"year": "2018", "q": "2018-09", "category": "36 - 40", "data": 1315},{"year": "2018", "q": "2018-09", "category": "51 - 55", "data": 1204},{"year": "2018", "q": "2018-09", "category": "56 - 60", "data": 743},{"year": "2018", "q": "2018-09", "category": "41 - 45", "data": 1553},{"year": "2018", "q": "2018-09", "category": "> 65", "data": 467},{"year": "2018", "q": "2018-09", "category": "31 - 35", "data": 928},{"year": "2018", "q": "2018-09", "category": "26 - 30", "data": 226},{"year": "2018", "q": "2018-08", "category": "61 - 65", "data": 2578},{"year": "2018", "q": "2018-08", "category": "56 - 60", "data": 744},{"year": "2018", "q": "2018-08", "category": "26 - 30", "data": 214},{"year": "2018", "q": "2018-08", "category": "25-", "data": 12},{"year": "2018", "q": "2018-08", "category": "> 65", "data": 503},{"year": "2018", "q": "2018-08", "category": "36 - 40", "data": 1303},{"year": "2018", "q": "2018-08", "category": "51 - 55", "data": 1198},{"year": "2018", "q": "2018-08", "category": "41 - 45", "data": 1540},{"year": "2018", "q": "2018-08", "category": "46 - 50", "data": 1476},{"year": "2018", "q": "2018-08", "category": "31 - 35", "data": 926},{"year": "2018", "q": "2018-07", "category": "31 - 35", "data": 920},{"year": "2018", "q": "2018-07", "category": "46 - 50", "data": 1466},{"year": "2018", "q": "2018-07", "category": "36 - 40", "data": 1296},{"year": "2018", "q": "2018-07", "category": "51 - 55", "data": 1198},{"year": "2018", "q": "2018-07", "category": "56 - 60", "data": 741},{"year": "2018", "q": "2018-07", "category": "25-", "data": 8},{"year": "2018", "q": "2018-07", "category": "61 - 65", "data": 2594},{"year": "2018", "q": "2018-07", "category": "> 65", "data": 535},{"year": "2018", "q": "2018-07", "category": "26 - 30", "data": 207},{"year": "2018", "q": "2018-07", "category": "41 - 45", "data": 1532},{"year": "2018", "q": "2018-06", "category": "51 - 55", "data": 1201},{"year": "2018", "q": "2018-06", "category": "26 - 30", "data": 205},{"year": "2018", "q": "2018-06", "category": "61 - 65", "data": 2612},{"year": "2018", "q": "2018-06", "category": "36 - 40", "data": 1298},{"year": "2018", "q": "2018-06", "category": "56 - 60", "data": 740},{"year": "2018", "q": "2018-06", "category": "41 - 45", "data": 1548},{"year": "2018", "q": "2018-06", "category": "46 - 50", "data": 1484},{"year": "2018", "q": "2018-06", "category": "25-", "data": 8},{"year": "2018", "q": "2018-06", "category": "> 65", "data": 575},{"year": "2018", "q": "2018-06", "category": "31 - 35", "data": 917},{"year": "2018", "q": "2018-05", "category": "46 - 50", "data": 1488},{"year": "2018", "q": "2018-05", "category": "25-", "data": 8},{"year": "2018", "q": "2018-05", "category": "26 - 30", "data": 205},{"year": "2018", "q": "2018-05", "category": "> 65", "data": 616},{"year": "2018", "q": "2018-05", "category": "41 - 45", "data": 1543},{"year": "2018", "q": "2018-05", "category": "31 - 35", "data": 912},{"year": "2018", "q": "2018-05", "category": "61 - 65", "data": 2628},{"year": "2018", "q": "2018-05", "category": "36 - 40", "data": 1290},{"year": "2018", "q": "2018-05", "category": "51 - 55", "data": 1201},{"year": "2018", "q": "2018-05", "category": "56 - 60", "data": 743},{"year": "2018", "q": "2018-04", "category": "> 65", "data": 678},{"year": "2018", "q": "2018-04", "category": "31 - 35", "data": 905},{"year": "2018", "q": "2018-04", "category": "46 - 50", "data": 1489},{"year": "2018", "q": "2018-04", "category": "25-", "data": 8},{"year": "2018", "q": "2018-04", "category": "61 - 65", "data": 2643},{"year": "2018", "q": "2018-04", "category": "51 - 55", "data": 1200},{"year": "2018", "q": "2018-04", "category": "56 - 60", "data": 741},{"year": "2018", "q": "2018-04", "category": "26 - 30", "data": 201},{"year": "2018", "q": "2018-04", "category": "36 - 40", "data": 1295},{"year": "2018", "q": "2018-04", "category": "41 - 45", "data": 1540},{"year": "2018", "q": "2018-03", "category": "26 - 30", "data": 200},{"year": "2018", "q": "2018-03", "category": "41 - 45", "data": 1540},{"year": "2018", "q": "2018-03", "category": "25-", "data": 8},{"year": "2018", "q": "2018-03", "category": "61 - 65", "data": 2661},{"year": "2018", "q": "2018-03", "category": "> 65", "data": 717},{"year": "2018", "q": "2018-03", "category": "36 - 40", "data": 1294},{"year": "2018", "q": "2018-03", "category": "51 - 55", "data": 1202},{"year": "2018", "q": "2018-03", "category": "56 - 60", "data": 741},{"year": "2018", "q": "2018-03", "category": "46 - 50", "data": 1490},{"year": "2018", "q": "2018-03", "category": "31 - 35", "data": 900},{"year": "2018", "q": "2018-02", "category": "41 - 45", "data": 1529},{"year": "2018", "q": "2018-02", "category": "56 - 60", "data": 737},{"year": "2018", "q": "2018-02", "category": "26 - 30", "data": 198},{"year": "2018", "q": "2018-02", "category": "46 - 50", "data": 1494},{"year": "2018", "q": "2018-02", "category": "> 65", "data": 751},{"year": "2018", "q": "2018-02", "category": "31 - 35", "data": 892},{"year": "2018", "q": "2018-02", "category": "36 - 40", "data": 1291},{"year": "2018", "q": "2018-02", "category": "51 - 55", "data": 1199},{"year": "2018", "q": "2018-02", "category": "25-", "data": 8},{"year": "2018", "q": "2018-02", "category": "61 - 65", "data": 2677},{"year": "2018", "q": "2018-01", "category": "61 - 65", "data": 2688},{"year": "2018", "q": "2018-01", "category": "> 65", "data": 781},{"year": "2018", "q": "2018-01", "category": "41 - 45", "data": 1526},{"year": "2018", "q": "2018-01", "category": "46 - 50", "data": 1494},{"year": "2018", "q": "2018-01", "category": "25-", "data": 8},{"year": "2018", "q": "2018-01", "category": "56 - 60", "data": 738},{"year": "2018", "q": "2018-01", "category": "31 - 35", "data": 878},{"year": "2018", "q": "2018-01", "category": "36 - 40", "data": 1283},{"year": "2018", "q": "2018-01", "category": "51 - 55", "data": 1201},{"year": "2018", "q": "2018-01", "category": "26 - 30", "data": 194}]